{"cameraMode":{"drawMode":0,"name":"Shaded","section":"Shading Mode"},"sceneLighting":true,"audioPlay":false,"sceneViewState":{"m_AlwaysRefresh":false,"showFog":true,"showSkybox":true,"showFlares":true,"showImageEffects":true,"showParticleSystems":true,"showVisualEffectGraphs":true,"m_FxEnabled":true},"in2DMode":false,"pivot":{"x":-265.4172668457031,"y":-203.09024047851563,"z":-53.98649597167969},"rotation":{"x":-0.40422090888023379,"y":-0.32091137766838076,"z":0.1539832204580307,"w":-0.8426033854484558},"size":146.5186767578125,"orthographic":false}