{"cameraMode":{"drawMode":0,"name":"Shaded","section":"Shading Mode"},"sceneLighting":true,"audioPlay":false,"sceneViewState":{"m_AlwaysRefresh":false,"showFog":true,"showSkybox":true,"showFlares":true,"showImageEffects":true,"showParticleSystems":true,"showVisualEffectGraphs":true,"m_FxEnabled":true},"in2DMode":false,"pivot":{"x":-227.54959106445313,"y":45.539306640625,"z":-297.5931701660156},"rotation":{"x":-0.45397502183914187,"y":-0.177703857421875,"z":0.09292963892221451,"w":-0.8681659698486328},"size":119.61400604248047,"orthographic":false}